.eslintrc.json
.prettierrc.json
.stylelintrc.json
CHANGES.rst
CONTRIBUTORS.rst
Gruntfile.js
LICENSE.GPL
LICENSE.rst
MANIFEST.in
README.rst
bootstrap-buildout.py
constraints.txt
constraints_plone51.txt
constraints_plone52.txt
package.json
requirements.txt
setup.cfg
setup.py
yarn.lock
docs/index.rst
docs/screenshots/gallery_modal.png
docs/screenshots/gallery_view.png
src/redturtle/__init__.py
src/redturtle.gallery.egg-info/PKG-INFO
src/redturtle.gallery.egg-info/SOURCES.txt
src/redturtle.gallery.egg-info/dependency_links.txt
src/redturtle.gallery.egg-info/entry_points.txt
src/redturtle.gallery.egg-info/namespace_packages.txt
src/redturtle.gallery.egg-info/not-zip-safe
src/redturtle.gallery.egg-info/requires.txt
src/redturtle.gallery.egg-info/top_level.txt
src/redturtle/gallery/__init__.py
src/redturtle/gallery/configure.zcml
src/redturtle/gallery/interfaces.py
src/redturtle/gallery/setuphandlers.py
src/redturtle/gallery/testing.py
src/redturtle/gallery/browser/__init__.py
src/redturtle/gallery/browser/configure.zcml
src/redturtle/gallery/browser/gallery.py
src/redturtle/gallery/browser/static/arrow.svg
src/redturtle/gallery/browser/static/css/redturtlegallery.css
src/redturtle/gallery/browser/static/css/redturtlegallery.css.map
src/redturtle/gallery/browser/static/js/bundle-compiled.js
src/redturtle/gallery/browser/static/js/bundle-compiled.js.map
src/redturtle/gallery/browser/static/js/integration.js
src/redturtle/gallery/browser/static/js/redturtle-gallery-bundle-compiled.min.js
src/redturtle/gallery/browser/static/js/redturtle-gallery-bundle-compiled.min.js.map
src/redturtle/gallery/browser/static/sass/_gallery_modal.scss
src/redturtle/gallery/browser/static/sass/_gallery_view.scss
src/redturtle/gallery/browser/static/sass/redturtlegallery.scss
src/redturtle/gallery/browser/templates/gallery_view.pt
src/redturtle/gallery/locales/redturtle.gallery.pot
src/redturtle/gallery/locales/update.sh
src/redturtle/gallery/locales/it/LC_MESSAGES/redturtle.gallery.po
src/redturtle/gallery/profiles/default/browserlayer.xml
src/redturtle/gallery/profiles/default/metadata.xml
src/redturtle/gallery/profiles/default/registry.xml
src/redturtle/gallery/profiles/default/types/Collection.xml
src/redturtle/gallery/profiles/default/types/Folder.xml
src/redturtle/gallery/profiles/uninstall/browserlayer.xml
