Metadata-Version: 2.1
Name: redturtle.gallery
Version: 2.2.1
Summary: Plone addon that adds a gallery view with a carousel made with slick.
Home-page: https://pypi.python.org/pypi/redturtle.gallery
Author: Redturtle Dev Team
Author-email: sviluppoplone@redturtle.it
License: GPL version 2
Keywords: Python Plone
Platform: UNKNOWN
Classifier: Environment :: Web Environment
Classifier: Framework :: Plone
Classifier: Framework :: Plone :: 5.1
Classifier: Framework :: Plone :: 5.2
Classifier: Programming Language :: Python
Classifier: Programming Language :: Python :: 2.7
Classifier: Programming Language :: Python :: 3.7
Classifier: Operating System :: OS Independent
Classifier: License :: OSI Approved :: GNU General Public License v2 (GPLv2)
Provides-Extra: test
